betters3/__init__.py
betters3-0.0.4.dist-info/LICENSE.txt
betters3-0.0.4.dist-info/WHEEL
betters3-0.0.4.dist-info/METADATA
betters3-0.0.4.dist-info/RECORD
