Metadata-Version: 2.1
Name: betters3
Version: 0.0.4
Summary: A wrapper of AWS S3 (boto3) that facilitate some operations.
Keywords: better,s3,better s3,betters3
Author: matgasp
Requires-Python: >= 3.9
Classifier: License :: OSI Approved :: MIT License
Classifier: Intended Audience :: Developers
Classifier: Natural Language :: English
Classifier: Development Status :: 5 - Production/Stable
Classifier: Operating System :: Microsoft :: Windows
Classifier: Topic :: Utilities
Classifier: Programming Language :: Python :: 3.9
Classifier: Programming Language :: Python :: 3.10
Classifier: Programming Language :: Python :: 3.11
Classifier: Programming Language :: Python :: 3.12
Requires-Dist: boto3
Requires-Dist: botocore
Project-URL: Issues, https://github.com/matgasp/betters3/issues
Project-URL: Repository, https://github.com/matgasp/betters3
